rhiza/__init__.py
rhiza/__main__.py
rhiza/cli.py
rhiza/models.py
rhiza/subprocess_utils.py
rhiza/_templates/basic/__init__.py.jinja2
rhiza/_templates/basic/main.py.jinja2
rhiza/_templates/basic/pyproject.toml.jinja2
rhiza/commands/__init__.py
rhiza/commands/init.py
rhiza/commands/materialize.py
rhiza/commands/migrate.py
rhiza/commands/summarise.py
rhiza/commands/uninstall.py
rhiza/commands/validate.py
rhiza/commands/welcome.py
rhiza-0.9.0.dist-info/METADATA
rhiza-0.9.0.dist-info/WHEEL
rhiza-0.9.0.dist-info/entry_points.txt
rhiza-0.9.0.dist-info/licenses/LICENSE
rhiza-0.9.0.dist-info/RECORD
