Metadata-Version: 2.4
Name: rhiza
Version: 0.9.0
Summary: Reusable configuration templates for modern Python projects
Project-URL: Homepage, https://github.com/jebel-quant/rhiza-cli
Project-URL: Repository, https://github.com/jebel-quant/rhiza-cli
Project-URL: Issues, https://github.com/jebel-quant/rhiza/issues-cli
Author: Thomas Schmelzer
License: MIT
License-File: LICENSE
Keywords: ci,configuration,ruff,taskfile,templates
Classifier: Intended Audience :: Developers
Classifier: License :: OSI Approved :: MIT License
Classifier: Programming Language :: Python :: 3
Classifier: Programming Language :: Python :: 3 :: Only
Classifier: Programming Language :: Python :: 3.11
Classifier: Programming Language :: Python :: 3.12
Classifier: Programming Language :: Python :: 3.13
Classifier: Programming Language :: Python :: 3.14
Classifier: Topic :: Software Development :: Build Tools
Requires-Python: >=3.11
Requires-Dist: jinja2>=3.1.0
Requires-Dist: loguru>=0.7.3
Requires-Dist: pyyaml==6.0.3
Requires-Dist: typer>=0.20.0
Provides-Extra: tools
Requires-Dist: rhiza-tools>=0.1.2; extra == 'tools'
